genotype/__init__.py
genotype/__main__.py
genotype/compat.py
genotype/constants.py
genotype/exc.py
genotype/log.py
genotype/cli/__init__.py
genotype/cli/base_cmd.py
genotype/cli/delete_cmd.py
genotype/cli/export_cmd.py
genotype/cli/init_cmd.py
genotype/cli/load_cmd.py
genotype/cli/match_cmd.py
genotype/cli/serve.py
genotype/cli/store_cmd.py
genotype/init/__init__.py
genotype/init/utils.py
genotype/load/__init__.py
genotype/load/excel.py
genotype/load/plate.py
genotype/load/vcf.py
genotype/match/__init__.py
genotype/match/core.py
genotype/server/__init__.py
genotype/server/admin.py
genotype/server/app.py
genotype/server/ext.py
genotype/server/genotypebp/__init__.py
genotype/server/genotypebp/views.py
genotype/store/__init__.py
genotype/store/api.py
genotype/store/export.py
genotype/store/models.py
genotype-3.0.0.dist-info/AUTHORS
genotype-3.0.0.dist-info/LICENSE
genotype-3.0.0.dist-info/METADATA
genotype-3.0.0.dist-info/WHEEL
genotype-3.0.0.dist-info/entry_points.txt
genotype-3.0.0.dist-info/top_level.txt
genotype-3.0.0.dist-info/RECORD
