Metadata-Version: 2.1
Name: genotype
Version: 3.0.0
Summary: genotype provides an automated pipipeline for comparinggenotypes from different assays.
Home-page: https://github.com/Clinical-Genomics/genotype
Author: Robin Andeer
Author-email: mans.magnusson@scilifelab.se
License: MIT
Keywords: genotype development
Platform: UNKNOWN
Classifier: Development Status :: 3 - Alpha
Classifier: Intended Audience :: Developers
Classifier: Topic :: Software Development
Classifier: License :: OSI Approved :: MIT License
Classifier: Programming Language :: Python :: 3.6
Classifier: Environment :: Console
Requires-Dist: cython
Requires-Dist: Alchy
Requires-Dist: SQLAlchemy
Requires-Dist: pymysql
Requires-Dist: cyvcf2 (<0.10.0)
Requires-Dist: xlrd
Requires-Dist: pysam (==0.15.2)
Requires-Dist: pyyaml
Requires-Dist: coloredlogs
Requires-Dist: click
Requires-Dist: Flask (>=1.1.1)
Requires-Dist: Flask-Bootstrap
Requires-Dist: Flask-Reverse-Proxy
Requires-Dist: Flask-SQLAlchemy (==2.1)
Requires-Dist: Flask-Alchy
Requires-Dist: Flask-Security
Requires-Dist: werkzeug (<1.0.0)
Requires-Dist: Flask-Login
Requires-Dist: Flask-Dance
Requires-Dist: ruamel.yaml
